mega_pytorch/__init__.py
mega_pytorch/autoregressive_wrapper.py
mega_pytorch/mega_pytorch.py
Mega_pytorch-0.1.0.dist-info/LICENSE
Mega_pytorch-0.1.0.dist-info/METADATA
Mega_pytorch-0.1.0.dist-info/WHEEL
Mega_pytorch-0.1.0.dist-info/top_level.txt
Mega_pytorch-0.1.0.dist-info/RECORD
